{"backend_name": "ibm_nairobi", "backend_version": "1.3.5", "last_update_date": "2024-05-27T15:45:40-03:00", "qubits": [[{"date": "2024-05-27T01:10:11-03:00", "name": "T1", "unit": "us", "value": 89.11932005215351}, {"date": "2024-05-27T01:11:16-03:00", "name": "T2", "unit": "us", "value": 15.788112289256514}, {"date": "2024-05-27T15:45:40-03:00", "name": "frequency", "unit": "GHz", "value": 5.259456041457937}, {"date": "2024-05-27T15:45:40-03:00", "name": "anharmonicity", "unit": "GHz", "value": -0.3398345949354833}, {"date": "2024-05-27T01:09:32-03:00", "name": "readout_error", "unit": "", "value": 0.05800000000000005}, {"date": "2024-05-27T01:09:32-03:00", "name": "prob_meas0_prep1", "unit": "", "value": 0.07899999999999996}, {"date": "2024-05-27T01:09:32-03:00", "name": "prob_meas1_prep0", "unit": "", "value": 0.037}, {"date": "2024-05-27T01:09:32-03:00", "name": "readout_length", "unit": "ns", "value": 5560.888888888889}], [{"date": "2024-05-27T01:10:11-03:00", "name": "T1", "unit": "us", "value": 87.26538034205313}, {"date": "2024-05-27T01:11:51-03:00", "name": "T2", "unit": "us", "value": 126.39674787282682}, {"date": "2024-05-27T15:45:40-03:00", "name": "frequency", "unit": "GHz", "value": 5.167930370694887}, {"date": "2024-05-27T15:45:40-03:00", "name": "anharmonicity", "unit": "GHz", "value": -0.3405834792685346}, {"date": "2024-05-27T01:09:32-03:00", "name": "readout_error", "unit": "", "value": 0.01990000000000003}, {"date": "2024-05-27T01:09:32-03:00", "name": "prob_meas0_prep1", "unit": "", "value": 0.02959999999999996}, {"date": "2024-05-27T01:09:32-03:00", "name": "prob_meas1_prep0", "unit": "", "value": 0.0102}, {"date": "2024-05-27T01:09:32-03:00", "name": "readout_length", "unit": "ns", "value": 5560.888888888889}], [{"date": "2024-05-27T01:10:11-03:00", "name": "T1", "unit": "us", "value": 133.23915779104922}, {"date": "2024-05-27T01:11:16-03:00", "name": "T2", "unit": "us", "value": 127.13613969430867}, {"date": "2024-05-27T15:45:40-03:00", "name": "frequency", "unit": "GHz", "value": 5.274522021242134}, {"date": "2024-05-27T15:45:40-03:00", "name": "anharmonicity", "unit": "GHz", "value": -0.3389036888077824}, {"date": "2024-05-27T01:09:32-03:00", "name": "readout_error", "unit": "", "value": 0.019299999999999984}, {"date": "2024-05-27T01:09:32-03:00", "name": "prob_meas0_prep1", "unit": "", "value": 0.02959999999999996}, {"date": "2024-05-27T01:09:32-03:00", "name": "prob_meas1_prep0", "unit": "", "value": 0.009}, {"date": "2024-05-27T01:09:32-03:00", "name": "readout_length", "unit": "ns", "value": 5560.888888888889}], [{"date": "2024-05-27T01:10:11-03:00", "name": "T1", "unit": "us", "value": 74.94187944204907}, {"date": "2024-05-27T01:11:16-03:00", "name": "T2", "unit": "us", "value": 75.99846916038535}, {"date": "2024-05-27T15:45:40-03:00", "name": "frequency", "unit": "GHz", "value": 5.0245135154881515}, {"date": "2024-05-27T15:45:40-03:00", "name": "anharmonicity", "unit": "GHz", "value": -0.34253037607049963}, {"date": "2024-05-27T01:09:32-03:00", "name": "readout_error", "unit": "", "value": 0.022299999999999986}, {"date": "2024-05-27T01:09:32-03:00", "name": "prob_meas0_prep1", "unit": "", "value": 0.03820000000000001}, {"date": "2024-05-27T01:09:32-03:00", "name": "prob_meas1_prep0", "unit": "", "value": 0.0064}, {"date": "2024-05-27T01:09:32-03:00", "name": "readout_length", "unit": "ns", "value": 5560.888888888889}], [{"date": "2024-05-27T01:10:11-03:00", "name": "T1", "unit": "us", "value": 131.22119282632082}, {"date": "2024-05-27T01:11:16-03:00", "name": "T2", "unit": "us", "value": 106.13173001967968}, {"date": "2024-05-27T15:45:40-03:00", "name": "frequency", "unit": "GHz", "value": 5.178162791748276}, {"date": "2024-05-27T15:45:40-03:00", "name": "anharmonicity", "unit": "GHz", "value": -0.34059039974918304}, {"date": "2024-05-27T01:09:32-03:00", "name": "readout_error", "unit": "", "value": 0.018299999999999983}, {"date": "2024-05-27T01:09:32-03:00", "name": "prob_meas0_prep1", "unit": "", "value": 0.02639999999999998}, {"date": "2024-05-27T01:09:32-03:00", "name": "prob_meas1_prep0", "unit": "", "value": 0.0102}, {"date": "2024-05-27T01:09:32-03:00", "name": "readout_length", "unit": "ns", "value": 5560.888888888889}], [{"date": "2024-05-27T01:10:11-03:00", "name": "T1", "unit": "us", "value": 80.65418374424905}, {"date": "2024-05-27T01:11:51-03:00", "name": "T2", "unit": "us", "value": 12.042600525667421}, {"date": "2024-05-27T15:45:40-03:00", "name": "frequency", "unit": "GHz", "value": 5.2926713833186385}, {"date": "2024-05-27T15:45:40-03:00", "name": "anharmonicity", "unit": "GHz", "value": -0.34053232043511467}, {"date": "2024-05-27T01:09:32-03:00", "name": "readout_error", "unit": "", "value": 0.022499999999999964}, {"date": "2024-05-27T01:09:32-03:00", "name": "prob_meas0_prep1", "unit": "", "value": 0.0342}, {"date": "2024-05-27T01:09:32-03:00", "name": "prob_meas1_prep0", "unit": "", "value": 0.010800000000000032}, {"date": "2024-05-27T01:09:32-03:00", "name": "readout_length", "unit": "ns", "value": 5560.888888888889}], [{"date": "2024-05-27T01:10:11-03:00", "name": "T1", "unit": "us", "value": 76.63770042270325}, {"date": "2024-05-27T01:11:16-03:00", "name": "T2", "unit": "us", "value": 126.20772862063315}, {"date": "2024-05-27T15:45:40-03:00", "name": "frequency", "unit": "GHz", "value": 5.128536512899253}, {"date": "2024-05-27T15:45:40-03:00", "name": "anharmonicity", "unit": "GHz", "value": -0.3404356760163406}, {"date": "2024-05-27T01:09:32-03:00", "name": "readout_error", "unit": "", "value": 0.025800000000000045}, {"date": "2024-05-27T01:09:32-03:00", "name": "prob_meas0_prep1", "unit": "", "value": 0.036800000000000055}, {"date": "2024-05-27T01:09:32-03:00", "name": "prob_meas1_prep0", "unit": "", "value": 0.0148}, {"date": "2024-05-27T01:09:32-03:00", "name": "readout_length", "unit": "ns", "value": 5560.888888888889}]], "gates": [{"qubits": [0], "gate": "id", "parameters": [{"date": "2024-05-27T01:12:20-03:00", "name": "gate_error", "unit": "", "value": 0.0003964904233122214}, {"date": "2024-05-27T01:12:20-03:00", "name": "gate_length", "unit": "ns", "value": 35.55555555555556}], "name": "id0"}, {"qubits": [1], "gate": "id", "parameters": [{"date": "2024-05-27T01:12:20-03:00", "name": "gate_error", "unit": "", "value": 0.00030662498367558497}, {"date": "2024-05-27T01:12:20-03:00", "name": "gate_length", "unit": "ns", "value": 35.55555555555556}], "name": "id1"}, {"qubits": [2], "gate": "id", "parameters": [{"date": "2024-05-27T01:13:38-03:00", "name": "gate_error", "unit": "", "value": 0.00020147699650026172}, {"date": "2024-05-27T01:13:38-03:00", "name": "gate_length", "unit": "ns", "value": 35.55555555555556}], "name": "id2"}, {"qubits": [3], "gate": "id", "parameters": [{"date": "2024-05-27T01:12:20-03:00", "name": "gate_error", "unit": "", "value": 0.00040829319361637104}, {"date": "2024-05-27T01:12:20-03:00", "name": "gate_length", "unit": "ns", "value": 35.55555555555556}], "name": "id3"}, {"qubits": [4], "gate": "id", "parameters": [{"date": "2024-05-27T01:12:20-03:00", "name": "gate_error", "unit": "", "value": 0.0005315540585991798}, {"date": "2024-05-27T01:12:20-03:00", "name": "gate_length", "unit": "ns", "value": 35.55555555555556}], "name": "id4"}, {"qubits": [5], "gate": "id", "parameters": [{"date": "2024-05-27T01:12:20-03:00", "name": "gate_error", "unit": "", "value": 0.0008354803813505588}, {"date": "2024-05-27T01:12:20-03:00", "name": "gate_length", "unit": "ns", "value": 35.55555555555556}], "name": "id5"}, {"qubits": [6], "gate": "id", "parameters": [{"date": "2024-05-27T01:13:38-03:00", "name": "gate_error", "unit": "", "value": 0.00026346335152001174}, {"date": "2024-05-27T01:13:38-03:00", "name": "gate_length", "unit": "ns", "value": 35.55555555555556}], "name": "id6"}, {"qubits": [0], "gate": "rz", "parameters": [{"date": "2024-05-27T15:45:40-03:00", "name": "gate_error", "unit": "", "value": 0}, {"date": "2024-05-27T15:45:40-03:00", "name": "gate_length", "unit": "ns", "value": 0}], "name": "rz0"}, {"qubits": [1], "gate": "rz", "parameters": [{"date": "2024-05-27T15:45:40-03:00", "name": "gate_error", "unit": "", "value": 0}, {"date": "2024-05-27T15:45:40-03:00", "name": "gate_length", "unit": "ns", "value": 0}], "name": "rz1"}, {"qubits": [2], "gate": "rz", "parameters": [{"date": "2024-05-27T15:45:40-03:00", "name": "gate_error", "unit": "", "value": 0}, {"date": "2024-05-27T15:45:40-03:00", "name": "gate_length", "unit": "ns", "value": 0}], "name": "rz2"}, {"qubits": [3], "gate": "rz", "parameters": [{"date": "2024-05-27T15:45:40-03:00", "name": "gate_error", "unit": "", "value": 0}, {"date": "2024-05-27T15:45:40-03:00", "name": "gate_length", "unit": "ns", "value": 0}], "name": "rz3"}, {"qubits": [4], "gate": "rz", "parameters": [{"date": "2024-05-27T15:45:40-03:00", "name": "gate_error", "unit": "", "value": 0}, {"date": "2024-05-27T15:45:40-03:00", "name": "gate_length", "unit": "ns", "value": 0}], "name": "rz4"}, {"qubits": [5], "gate": "rz", "parameters": [{"date": "2024-05-27T15:45:40-03:00", "name": "gate_error", "unit": "", "value": 0}, {"date": "2024-05-27T15:45:40-03:00", "name": "gate_length", "unit": "ns", "value": 0}], "name": "rz5"}, {"qubits": [6], "gate": "rz", "parameters": [{"date": "2024-05-27T15:45:40-03:00", "name": "gate_error", "unit": "", "value": 0}, {"date": "2024-05-27T15:45:40-03:00", "name": "gate_length", "unit": "ns", "value": 0}], "name": "rz6"}, {"qubits": [0], "gate": "sx", "parameters": [{"date": "2024-05-27T01:12:20-03:00", "name": "gate_error", "unit": "", "value": 0.0003964904233122214}, {"date": "2024-05-27T01:12:20-03:00", "name": "gate_length", "unit": "ns", "value": 35.55555555555556}], "name": "sx0"}, {"qubits": [1], "gate": "sx", "parameters": [{"date": "2024-05-27T01:12:20-03:00", "name": "gate_error", "unit": "", "value": 0.00030662498367558497}, {"date": "2024-05-27T01:12:20-03:00", "name": "gate_length", "unit": "ns", "value": 35.55555555555556}], "name": "sx1"}, {"qubits": [2], "gate": "sx", "parameters": [{"date": "2024-05-27T01:13:38-03:00", "name": "gate_error", "unit": "", "value": 0.00020147699650026172}, {"date": "2024-05-27T01:13:38-03:00", "name": "gate_length", "unit": "ns", "value": 35.55555555555556}], "name": "sx2"}, {"qubits": [3], "gate": "sx", "parameters": [{"date": "2024-05-27T01:12:20-03:00", "name": "gate_error", "unit": "", "value": 0.00040829319361637104}, {"date": "2024-05-27T01:12:20-03:00", "name": "gate_length", "unit": "ns", "value": 35.55555555555556}], "name": "sx3"}, {"qubits": [4], "gate": "sx", "parameters": [{"date": "2024-05-27T01:12:20-03:00", "name": "gate_error", "unit": "", "value": 0.0005315540585991798}, {"date": "2024-05-27T01:12:20-03:00", "name": "gate_length", "unit": "ns", "value": 35.55555555555556}], "name": "sx4"}, {"qubits": [5], "gate": "sx", "parameters": [{"date": "2024-05-27T01:12:20-03:00", "name": "gate_error", "unit": "", "value": 0.0008354803813505588}, {"date": "2024-05-27T01:12:20-03:00", "name": "gate_length", "unit": "ns", "value": 35.55555555555556}], "name": "sx5"}, {"qubits": [6], "gate": "sx", "parameters": [{"date": "2024-05-27T01:13:38-03:00", "name": "gate_error", "unit": "", "value": 0.00026346335152001174}, {"date": "2024-05-27T01:13:38-03:00", "name": "gate_length", "unit": "ns", "value": 35.55555555555556}], "name": "sx6"}, {"qubits": [0], "gate": "x", "parameters": [{"date": "2024-05-27T01:12:20-03:00", "name": "gate_error", "unit": "", "value": 0.0003964904233122214}, {"date": "2024-05-27T01:12:20-03:00", "name": "gate_length", "unit": "ns", "value": 35.55555555555556}], "name": "x0"}, {"qubits": [1], "gate": "x", "parameters": [{"date": "2024-05-27T01:12:20-03:00", "name": "gate_error", "unit": "", "value": 0.00030662498367558497}, {"date": "2024-05-27T01:12:20-03:00", "name": "gate_length", "unit": "ns", "value": 35.55555555555556}], "name": "x1"}, {"qubits": [2], "gate": "x", "parameters": [{"date": "2024-05-27T01:13:38-03:00", "name": "gate_error", "unit": "", "value": 0.00020147699650026172}, {"date": "2024-05-27T01:13:38-03:00", "name": "gate_length", "unit": "ns", "value": 35.55555555555556}], "name": "x2"}, {"qubits": [3], "gate": "x", "parameters": [{"date": "2024-05-27T01:12:20-03:00", "name": "gate_error", "unit": "", "value": 0.00040829319361637104}, {"date": "2024-05-27T01:12:20-03:00", "name": "gate_length", "unit": "ns", "value": 35.55555555555556}], "name": "x3"}, {"qubits": [4], "gate": "x", "parameters": [{"date": "2024-05-27T01:12:20-03:00", "name": "gate_error", "unit": "", "value": 0.0005315540585991798}, {"date": "2024-05-27T01:12:20-03:00", "name": "gate_length", "unit": "ns", "value": 35.55555555555556}], "name": "x4"}, {"qubits": [5], "gate": "x", "parameters": [{"date": "2024-05-27T01:12:20-03:00", "name": "gate_error", "unit": "", "value": 0.0008354803813505588}, {"date": "2024-05-27T01:12:20-03:00", "name": "gate_length", "unit": "ns", "value": 35.55555555555556}], "name": "x5"}, {"qubits": [6], "gate": "x", "parameters": [{"date": "2024-05-27T01:13:38-03:00", "name": "gate_error", "unit": "", "value": 0.00026346335152001174}, {"date": "2024-05-27T01:13:38-03:00", "name": "gate_length", "unit": "ns", "value": 35.55555555555556}], "name": "x6"}, {"qubits": [6, 5], "gate": "cx", "parameters": [{"date": "2024-05-27T01:27:38-03:00", "name": "gate_error", "unit": "", "value": 0.010660006612845774}, {"date": "2024-05-27T01:27:38-03:00", "name": "gate_length", "unit": "ns", "value": 305.77777777777777}], "name": "cx6_5"}, {"qubits": [5, 6], "gate": "cx", "parameters": [{"date": "2024-05-27T01:27:38-03:00", "name": "gate_error", "unit": "", "value": 0.010660006612845774}, {"date": "2024-05-27T01:27:38-03:00", "name": "gate_length", "unit": "ns", "value": 341.3333333333333}], "name": "cx5_6"}, {"qubits": [5, 4], "gate": "cx", "parameters": [{"date": "2024-05-27T01:26:24-03:00", "name": "gate_error", "unit": "", "value": 0.007004886073433525}, {"date": "2024-05-27T01:26:24-03:00", "name": "gate_length", "unit": "ns", "value": 277.3333333333333}], "name": "cx5_4"}, {"qubits": [4, 5], "gate": "cx", "parameters": [{"date": "2024-05-27T01:26:24-03:00", "name": "gate_error", "unit": "", "value": 0.007004886073433525}, {"date": "2024-05-27T01:26:24-03:00", "name": "gate_length", "unit": "ns", "value": 312.88888888888886}], "name": "cx4_5"}, {"qubits": [5, 3], "gate": "cx", "parameters": [{"date": "2024-05-27T01:25:10-03:00", "name": "gate_error", "unit": "", "value": 0.012572268228634498}, {"date": "2024-05-27T01:25:10-03:00", "name": "gate_length", "unit": "ns", "value": 604.4444444444445}], "name": "cx5_3"}, {"qubits": [3, 5], "gate": "cx", "parameters": [{"date": "2024-05-27T01:25:10-03:00", "name": "gate_error", "unit": "", "value": 0.012572268228634498}, {"date": "2024-05-27T01:25:10-03:00", "name": "gate_length", "unit": "ns", "value": 640}], "name": "cx3_5"}, {"qubits": [1, 3], "gate": "cx", "parameters": [{"date": "2024-05-27T01:23:57-03:00", "name": "gate_error", "unit": "", "value": 0.006790988836364892}, {"date": "2024-05-27T01:23:57-03:00", "name": "gate_length", "unit": "ns", "value": 270.22222222222223}], "name": "cx1_3"}, {"qubits": [3, 1], "gate": "cx", "parameters": [{"date": "2024-05-27T01:23:57-03:00", "name": "gate_error", "unit": "", "value": 0.006790988836364892}, {"date": "2024-05-27T01:23:57-03:00", "name": "gate_length", "unit": "ns", "value": 305.77777777777777}], "name": "cx3_1"}, {"qubits": [2, 1], "gate": "cx", "parameters": [{"date": "2024-05-27T01:22:43-03:00", "name": "gate_error", "unit": "", "value": 0.006982735263829087}, {"date": "2024-05-27T01:22:43-03:00", "name": "gate_length", "unit": "ns", "value": 391.1111111111111}], "name": "cx2_1"}, {"qubits": [1, 2], "gate": "cx", "parameters": [{"date": "2024-05-27T01:22:43-03:00", "name": "gate_error", "unit": "", "value": 0.006982735263829087}, {"date": "2024-05-27T01:22:43-03:00", "name": "gate_length", "unit": "ns", "value": 426.66666666666663}], "name": "cx1_2"}, {"qubits": [0, 1], "gate": "cx", "parameters": [{"date": "2024-05-27T01:21:30-03:00", "name": "gate_error", "unit": "", "value": 0.008594115909420164}, {"date": "2024-05-27T01:21:30-03:00", "name": "gate_length", "unit": "ns", "value": 248.88888888888889}], "name": "cx0_1"}, {"qubits": [1, 0], "gate": "cx", "parameters": [{"date": "2024-05-27T01:21:30-03:00", "name": "gate_error", "unit": "", "value": 0.008594115909420164}, {"date": "2024-05-27T01:21:30-03:00", "name": "gate_length", "unit": "ns", "value": 284.44444444444446}], "name": "cx1_0"}, {"qubits": [0], "gate": "reset", "parameters": [{"date": "2024-05-27T15:45:40-03:00", "name": "gate_length", "unit": "ns", "value": 5596.444444444444}], "name": "reset0"}, {"qubits": [1], "gate": "reset", "parameters": [{"date": "2024-05-27T15:45:40-03:00", "name": "gate_length", "unit": "ns", "value": 5596.444444444444}], "name": "reset1"}, {"qubits": [2], "gate": "reset", "parameters": [{"date": "2024-05-27T15:45:40-03:00", "name": "gate_length", "unit": "ns", "value": 5596.444444444444}], "name": "reset2"}, {"qubits": [3], "gate": "reset", "parameters": [{"date": "2024-05-27T15:45:40-03:00", "name": "gate_length", "unit": "ns", "value": 5596.444444444444}], "name": "reset3"}, {"qubits": [4], "gate": "reset", "parameters": [{"date": "2024-05-27T15:45:40-03:00", "name": "gate_length", "unit": "ns", "value": 5596.444444444444}], "name": "reset4"}, {"qubits": [5], "gate": "reset", "parameters": [{"date": "2024-05-27T15:45:40-03:00", "name": "gate_length", "unit": "ns", "value": 5596.444444444444}], "name": "reset5"}, {"qubits": [6], "gate": "reset", "parameters": [{"date": "2024-05-27T15:45:40-03:00", "name": "gate_length", "unit": "ns", "value": 5596.444444444444}], "name": "reset6"}], "general": [{"date": "2024-05-27T15:45:40-03:00", "name": "jq_01", "unit": "GHz", "value": 0.002424365147211133}, {"date": "2024-05-27T15:45:40-03:00", "name": "zz_01", "unit": "GHz", "value": -7.44245306702971e-05}, {"date": "2024-05-27T15:45:40-03:00", "name": "jq_12", "unit": "GHz", "value": 0.003299484405707071}, {"date": "2024-05-27T15:45:40-03:00", "name": "zz_12", "unit": "GHz", "value": -0.00014195540167377774}, {"date": "2024-05-27T15:45:40-03:00", "name": "jq_45", "unit": "GHz", "value": 0.0033842854076643666}, {"date": "2024-05-27T15:45:40-03:00", "name": "zz_45", "unit": "GHz", "value": -0.00015121873088148923}, {"date": "2024-05-27T15:45:40-03:00", "name": "jq_56", "unit": "GHz", "value": 0.003298540438896099}, {"date": "2024-05-27T15:45:40-03:00", "name": "zz_56", "unit": "GHz", "value": -0.00016524485201342335}, {"date": "2024-05-27T15:45:40-03:00", "name": "jq_13", "unit": "GHz", "value": 0.0032526977547337834}, {"date": "2024-05-27T15:45:40-03:00", "name": "zz_13", "unit": "GHz", "value": -0.00015085979775338062}, {"date": "2024-05-27T15:45:40-03:00", "name": "jq_35", "unit": "GHz", "value": 0.0023906436500284963}, {"date": "2024-05-27T15:45:40-03:00", "name": "zz_35", "unit": "GHz", "value": -0.0001688529115642526}], "general_qlists": []}